odoo10_addon_l10n_fr_chorus_ubl-10.0.1.0.0.99.dev12-py3.8-nspkg.pth
odoo/addons/l10n_fr_chorus_ubl/README.rst
odoo/addons/l10n_fr_chorus_ubl/__init__.py
odoo/addons/l10n_fr_chorus_ubl/__manifest__.py
odoo/addons/l10n_fr_chorus_ubl/i18n/fr.po
odoo/addons/l10n_fr_chorus_ubl/i18n/l10n_fr_chorus_ubl.pot
odoo/addons/l10n_fr_chorus_ubl/i18n/nb_NO.po
odoo/addons/l10n_fr_chorus_ubl/models/__init__.py
odoo/addons/l10n_fr_chorus_ubl/models/account_invoice.py
odoo/addons/l10n_fr_chorus_ubl/models/chorus_flow.py
odoo/addons/l10n_fr_chorus_ubl/models/company.py
odoo/addons/l10n_fr_chorus_ubl/models/ubl.py
odoo/addons/l10n_fr_chorus_ubl/readme/CONFIGURE.rst
odoo/addons/l10n_fr_chorus_ubl/readme/CONTRIBUTORS.rst
odoo/addons/l10n_fr_chorus_ubl/readme/DESCRIPTION.rst
odoo/addons/l10n_fr_chorus_ubl/readme/USAGE.rst
odoo/addons/l10n_fr_chorus_ubl/static/description/icon.png
odoo/addons/l10n_fr_chorus_ubl/static/description/index.html
odoo/addons/l10n_fr_chorus_ubl/tests/__init__.py
odoo/addons/l10n_fr_chorus_ubl/tests/test_chorus_ubl.py
odoo10_addon_l10n_fr_chorus_ubl-10.0.1.0.0.99.dev12.dist-info/METADATA
odoo10_addon_l10n_fr_chorus_ubl-10.0.1.0.0.99.dev12.dist-info/WHEEL
odoo10_addon_l10n_fr_chorus_ubl-10.0.1.0.0.99.dev12.dist-info/namespace_packages.txt
odoo10_addon_l10n_fr_chorus_ubl-10.0.1.0.0.99.dev12.dist-info/top_level.txt
odoo10_addon_l10n_fr_chorus_ubl-10.0.1.0.0.99.dev12.dist-info/RECORD
