Metadata-Version: 2.1
Name: odoo10-addon-l10n-fr-chorus-ubl
Version: 10.0.1.0.0.99.dev12
Summary: Generate Chorus-compliant UBL e-invoices
Home-page: https://github.com/OCA/l10n-france
Author: Akretion,Odoo Community Association (OCA)
Author-email: support@odoo-community.org
License: AGPL-3
Platform: UNKNOWN
Classifier: Programming Language :: Python
Classifier: Framework :: Odoo
Classifier: Framework :: Odoo :: 10.0
Classifier: License :: OSI Approved :: GNU Affero General Public License v3
Requires-Python: ~=2.7
Requires-Dist: odoo10-addon-account-invoice-ubl
Requires-Dist: odoo10-addon-l10n-fr-chorus-account
Requires-Dist: odoo <10.1dev,>=10.0
